domain_types_linter/__init__.py
domain_types_linter/cli.py
domain_types_linter/flake8_plugin.py
domain_types_linter/main.py
domain_types_linter/py.typed
domain_types_linter/types_and_codes.py
domain_types_linter-1.0.0.dist-info/METADATA
domain_types_linter-1.0.0.dist-info/WHEEL
domain_types_linter-1.0.0.dist-info/entry_points.txt
domain_types_linter-1.0.0.dist-info/RECORD
