Metadata-Version: 2.4
Name: domain-types-linter
Version: 1.0.0
Summary: A static code analyzer that enforces the use of domain-specific types in business logic code instead of universal types
Project-URL: Homepage, https://github.com/pavelmaksimov/domain-types-linter
Project-URL: Bug Tracker, https://github.com/pavelmaksimov/domain-types-linter/issues
Author-email: Pavel Maksimov <vur21@yandex.ru>
Requires-Python: >=3.10
Provides-Extra: flake8
Requires-Dist: flake8>=7.2.0; extra == 'flake8'
